MANIFEST.in
setup.cfg
setup.py
eReuse_DeviceHub.egg-info/PKG-INFO
eReuse_DeviceHub.egg-info/SOURCES.txt
eReuse_DeviceHub.egg-info/dependency_links.txt
eReuse_DeviceHub.egg-info/requires.txt
eReuse_DeviceHub.egg-info/top_level.txt
ereuse_devicehub/__init__.py
ereuse_devicehub/data_layer.py
ereuse_devicehub/default_settings.py
ereuse_devicehub/error_handler.py
ereuse_devicehub/exceptions.py
ereuse_devicehub/flask_decorators.py
ereuse_devicehub/flaskapp.py
ereuse_devicehub/hooks.py
ereuse_devicehub/request.py
ereuse_devicehub/rest.py
ereuse_devicehub/static.py
ereuse_devicehub/utils.py
ereuse_devicehub/aggregation/__init__.py
ereuse_devicehub/aggregation/aggregation.py
ereuse_devicehub/aggregation/settings.py
ereuse_devicehub/resources/__init__.py
ereuse_devicehub/resources/condition.py
ereuse_devicehub/resources/domain.py
ereuse_devicehub/resources/hooks.py
ereuse_devicehub/resources/resource.py
ereuse_devicehub/resources/schema.py
ereuse_devicehub/resources/account/__init__.py
ereuse_devicehub/resources/account/domain.py
ereuse_devicehub/resources/account/hooks.py
ereuse_devicehub/resources/account/role.py
ereuse_devicehub/resources/account/settings.py
ereuse_devicehub/resources/account/login/__init__.py
ereuse_devicehub/resources/account/login/settings.py
ereuse_devicehub/resources/device/__init__.py
ereuse_devicehub/resources/device/benchmark_settings.py
ereuse_devicehub/resources/device/domain.py
ereuse_devicehub/resources/device/exceptions.py
ereuse_devicehub/resources/device/hooks.py
ereuse_devicehub/resources/device/schema.py
ereuse_devicehub/resources/device/settings.py
ereuse_devicehub/resources/device/component/__init__.py
ereuse_devicehub/resources/device/component/component.py
ereuse_devicehub/resources/device/component/domain.py
ereuse_devicehub/resources/device/component/settings.py
ereuse_devicehub/resources/device/component/graphic_card/__init__.py
ereuse_devicehub/resources/device/component/graphic_card/settings.py
ereuse_devicehub/resources/device/component/hard_drive/__init__.py
ereuse_devicehub/resources/device/component/hard_drive/settings.py
ereuse_devicehub/resources/device/component/motherboard/__init__.py
