Metadata-Version: 1.1
Name: eReuse-DeviceHub
Version: 0.1.1
Summary: DeviceHub is a system to manage devices focused in reusing them. 
Home-page: https://github.com/eReuse/DeviceHub
Author: eReuse.org team
Author-email: x.bustamante@ereuse.org
License: AGPLv3 License
Keywords: eReuse.org DeviceHub devices devicehub reuse recycle it asset management
Platform: UNKNOWN
Classifier: Development Status :: 3 - Alpha
Classifier: Environment :: Web Environment
Classifier: Framework :: Flask
Classifier: Intended Audience :: Manufacturing
Classifier: License :: OSI Approved :: GNU Affero General Public License v3
Classifier: Natural Language :: English
Classifier: Operating System :: OS Independent
Classifier: Programming Language :: Python :: 3.4
Classifier: Programming Language :: Python :: 3.5
Classifier: Topic :: Office/Business
Classifier: Topic :: Internet :: WWW/HTTP
Classifier: Topic :: Internet :: WWW/HTTP :: Dynamic Content
